apisani_test_project_25070208/__init__.py
apisani_test_project_25070208-0.0.1.dist-info/LICENSE
apisani_test_project_25070208-0.0.1.dist-info/METADATA
apisani_test_project_25070208-0.0.1.dist-info/WHEEL
apisani_test_project_25070208-0.0.1.dist-info/RECORD
