Metadata-Version: 2.3
Name: apisani-test-project-25070208
Version: 0.0.1
Summary: A short description of the project
Author: Antonio Pisani
Author-email: antonio.pisani@gmail.com
Requires-Python: >=3.10,<4.0
Classifier: Programming Language :: Python :: 3
Classifier: Programming Language :: Python :: 3.10
Classifier: Programming Language :: Python :: 3.11
Classifier: Programming Language :: Python :: 3.12
Classifier: Programming Language :: Python :: 3.13
Project-URL: Documentation, https://apisani-test-project-25070208.readthedocs.io/
Project-URL: Issue Tracker, https://github.com/apisani1/apisani-test-project-25070208/issues
Project-URL: Release Notes, https://github.com/apisani1/apisani-test-project-25070208/releases
Project-URL: Source Code, https://github.com/apisani1/apisani-test-project-25070208
